paypal_agent_toolkit/__init__.py
paypal_agent_toolkit/bedrock/toolkit.py
paypal_agent_toolkit/crewai/tool.py
paypal_agent_toolkit/crewai/toolkit.py
paypal_agent_toolkit/langchain/tool.py
paypal_agent_toolkit/langchain/toolkit.py
paypal_agent_toolkit/openai/__init__.py
paypal_agent_toolkit/openai/tool.py
paypal_agent_toolkit/openai/toolkit.py
paypal_agent_toolkit/shared/__init__.py
paypal_agent_toolkit/shared/api.py
paypal_agent_toolkit/shared/configuration.py
paypal_agent_toolkit/shared/constants.py
paypal_agent_toolkit/shared/logger_util.py
paypal_agent_toolkit/shared/paypal_client.py
paypal_agent_toolkit/shared/regex.py
paypal_agent_toolkit/shared/telemetry.py
paypal_agent_toolkit/shared/tools.py
paypal_agent_toolkit/shared/disputes/parameters.py
paypal_agent_toolkit/shared/disputes/prompts.py
paypal_agent_toolkit/shared/disputes/tool_handlers.py
paypal_agent_toolkit/shared/insights/parameters.py
paypal_agent_toolkit/shared/insights/prompts.py
paypal_agent_toolkit/shared/insights/tool_handlers.py
paypal_agent_toolkit/shared/invoices/parameters.py
paypal_agent_toolkit/shared/invoices/prompts.py
paypal_agent_toolkit/shared/invoices/tool_handlers.py
paypal_agent_toolkit/shared/orders/__init__.py
paypal_agent_toolkit/shared/orders/parameters.py
paypal_agent_toolkit/shared/orders/payload_util.py
paypal_agent_toolkit/shared/orders/prompts.py
paypal_agent_toolkit/shared/orders/tool_handlers.py
paypal_agent_toolkit/shared/subscriptions/__init__.py
paypal_agent_toolkit/shared/subscriptions/parameters.py
paypal_agent_toolkit/shared/subscriptions/prompts.py
paypal_agent_toolkit/shared/subscriptions/tool_handlers.py
paypal_agent_toolkit/shared/tracking/parameters.py
paypal_agent_toolkit/shared/tracking/prompts.py
paypal_agent_toolkit/shared/tracking/tool_handlers.py
paypal_agent_toolkit/shared/transactions/parameters.py
paypal_agent_toolkit/shared/transactions/prompt.py
paypal_agent_toolkit/shared/transactions/tool_handlers.py
paypal_agent_toolkit-1.8.0.dist-info/METADATA
paypal_agent_toolkit-1.8.0.dist-info/WHEEL
paypal_agent_toolkit-1.8.0.dist-info/top_level.txt
paypal_agent_toolkit-1.8.0.dist-info/RECORD
