Metadata-Version: 2.4
Name: paypal-agent-toolkit
Version: 1.8.0
Summary: A toolkit for agent interactions with PayPal API.
Author-email: PayPal <support@paypal.com>
Project-URL: Bug Tracker, https://github.com/paypal/agent-toolkit/issues
Project-URL: Source Code, https://github.com/paypal/agent-toolkit
Keywords: paypal,payments,checkout,api
Requires-Python: >=3.11
Requires-Dist: openai-agents==0.0.2
Requires-Dist: langchain==0.3.23
Requires-Dist: crewai-tools==0.13.2
Requires-Dist: httpx>=0.26.0
Requires-Dist: requests>=2.31.0
Requires-Dist: python-dotenv>=1.0.1
Requires-Dist: pydantic>=2.10
